CHANGELOG.md
MANIFEST.in
README.md
setup.py
stdeb.cfg
groot_tools/__init__.py
groot_tools.egg-info/PKG-INFO
groot_tools.egg-info/SOURCES.txt
groot_tools.egg-info/dependency_links.txt
groot_tools.egg-info/requires.txt
groot_tools.egg-info/top_level.txt
scripts/groot-cfind
scripts/groot-docker-build
scripts/groot-docker-enter