Metadata-Version: 1.2
Name: groot-tools
Version: 0.3.2
Summary: groot's swiss army knife
Home-page: http://github.com/stonier/groot_tools
Author: Daniel Stonier
Author-email: d.stonier@gmail.com
Maintainer: Daniel Stonier
Maintainer-email: d.stonier@gmail.com
License: BSD
Keywords: catkin
Platform: UNKNOWN
Classifier: Environment :: Console
Classifier: Intended Audience :: Developers
Classifier: License :: OSI Approved :: BSD License
Classifier: Programming Language :: Python
Classifier: Topic :: System :: Systems Administration
Classifier: Topic :: Utilities
